tutor_contrib_branding-19.0.2.dist-info/licenses/LICENSE.txt
tutorbranding/__about__.py
tutorbranding/__init__.py
tutorbranding/plugin.py
tutorbranding/patches/.gitignore
tutorbranding/patches/mfe-dockerfile-post-npm-install
tutorbranding/patches/mfe-dockerfile-pre-npm-install
tutorbranding/patches/mfe-dockerfile-pre-npm-install-account
tutorbranding/patches/mfe-dockerfile-pre-npm-install-authn
tutorbranding/patches/mfe-dockerfile-pre-npm-install-communications
tutorbranding/patches/mfe-dockerfile-pre-npm-install-course-authoring
tutorbranding/patches/mfe-dockerfile-pre-npm-install-discussions
tutorbranding/patches/mfe-dockerfile-pre-npm-install-gradebook
tutorbranding/patches/mfe-dockerfile-pre-npm-install-learner-dashboard
tutorbranding/patches/mfe-dockerfile-pre-npm-install-learning
tutorbranding/patches/mfe-dockerfile-pre-npm-install-ora-grading
tutorbranding/patches/mfe-dockerfile-pre-npm-install-profile
tutorbranding/patches/mfe-lms-common-settings
tutorbranding/patches/openedx-dockerfile-minimal
tutorbranding/patches/openedx-dockerfile-pre-assets
tutorbranding/templates/brand-openedx/.gitignore
tutorbranding/templates/brand-openedx/LICENSE
tutorbranding/templates/brand-openedx/README.rst
tutorbranding/templates/brand-openedx/favicon.ico
tutorbranding/templates/brand-openedx/logo-trademark.png
tutorbranding/templates/brand-openedx/logo-trademark.svg
tutorbranding/templates/brand-openedx/logo-white.png
tutorbranding/templates/brand-openedx/logo-white.svg
tutorbranding/templates/brand-openedx/logo.png
tutorbranding/templates/brand-openedx/logo.svg
tutorbranding/templates/brand-openedx/package-lock.json
tutorbranding/templates/brand-openedx/package.json
tutorbranding/templates/brand-openedx/paragon/_fonts.scss
tutorbranding/templates/brand-openedx/paragon/_overrides.scss
tutorbranding/templates/brand-openedx/paragon/_variables.scss
tutorbranding/templates/brand-openedx-learner-dashboard/.gitignore
tutorbranding/templates/brand-openedx-learner-dashboard/LICENSE
tutor_contrib_branding-19.0.2.dist-info/METADATA
tutor_contrib_branding-19.0.2.dist-info/WHEEL
tutor_contrib_branding-19.0.2.dist-info/entry_points.txt
tutor_contrib_branding-19.0.2.dist-info/top_level.txt
tutor_contrib_branding-19.0.2.dist-info/RECORD
