Metadata-Version: 2.4
Name: tutor-contrib-branding
Version: 19.0.2
Summary: Tutor plugin that simplifies branding an Open edX instance
Home-page: https://github.com/aulasneo/tutor-contrib-branding
Author: Aulasneo
Author-email: andres@aulasneo.com
License: AGPLv3
Project-URL: Code, https://github.com/aulasneo/tutor-contrib-brandingh
Project-URL: Issue tracker, https://github.com/aulasneo/tutor-contrib-branding/issues
Classifier: Development Status :: 3 - Alpha
Classifier: Intended Audience :: Developers
Classifier: License :: OSI Approved :: GNU Affero General Public License v3
Classifier: Operating System :: OS Independent
Classifier: Programming Language :: Python
Classifier: Programming Language :: Python :: 3.7
Classifier: Programming Language :: Python :: 3.8
Classifier: Programming Language :: Python :: 3.9
Classifier: Programming Language :: Python :: 3.10
Requires-Python: >=3.7
License-File: LICENSE.txt
Requires-Dist: tutor<20.0.0,>=19.0.0
Requires-Dist: urllib3==1.26.6
Dynamic: author
Dynamic: author-email
Dynamic: classifier
Dynamic: description
Dynamic: description-content-type
Dynamic: home-page
Dynamic: license
Dynamic: license-file
Dynamic: project-url
Dynamic: requires-dist
Dynamic: requires-python
Dynamic: summary
